python_interpreter_mcp/__init__.py
python_interpreter_mcp/__main__.py
python_interpreter_mcp/runner.py
python_interpreter_mcp/server.py
python_interpreter_mcp-0.1.0.dist-info/METADATA
python_interpreter_mcp-0.1.0.dist-info/WHEEL
python_interpreter_mcp-0.1.0.dist-info/entry_points.txt
python_interpreter_mcp-0.1.0.dist-info/RECORD
