Metadata-Version: 2.4
Name: python-interpreter-mcp
Version: 0.1.0
Summary: A Model Context Server providing simple features to automate python script execution via LLMs
Author: Bimal Paudel
Keywords: automation,llm,mcp,python
Requires-Python: >=3.13
Requires-Dist: mcp[cli]>=1.6.0
